twitterpastcrawler/__init__.py
twitterpastcrawler/crawler.py
twitterpastcrawler/twitterpastcrawler.py
twitterpastcrawler/useragents_linux.dat
twitterpastcrawler/useragents_mac.dat
twitterpastcrawler/useragents_windows.dat
twitterpastcrawler-0.0.6.dist-info/DESCRIPTION.rst
twitterpastcrawler-0.0.6.dist-info/METADATA
twitterpastcrawler-0.0.6.dist-info/RECORD
twitterpastcrawler-0.0.6.dist-info/WHEEL
twitterpastcrawler-0.0.6.dist-info/metadata.json
twitterpastcrawler-0.0.6.dist-info/top_level.txt
