Metadata-Version: 2.0
Name: twitterpastcrawler
Version: 0.0.6
Summary: A crawler that can crawl and accumulate past tweets without using the official API.
Home-page: https://github.com/keitakurita/twitter_past_crawler
Author: Keita Kurita
Author-email: UNKNOWN
License: MIT
Keywords: twitter crawler
Platform: UNKNOWN
Classifier: Development Status :: 3 - Alpha
Classifier: Programming Language :: Python :: 3.4
Classifier: Programming Language :: Python :: 3.5
Requires-Dist: beautifulsoup4
Requires-Dist: lxml
Requires-Dist: requests
